LICENSE
MANIFEST.in
README.md
requirements.txt
setup.py
github_console/__init__.py
github_console/github.py
github_console/key.py
github_console/repo.py
github_console.egg-info/PKG-INFO
github_console.egg-info/SOURCES.txt
github_console.egg-info/dependency_links.txt
github_console.egg-info/entry_points.txt
github_console.egg-info/not-zip-safe
github_console.egg-info/requires.txt
github_console.egg-info/top_level.txt